scatterd/__init__.py
scatterd/examples.py
scatterd/scatterd.py
scatterd-1.3.9.dist-info/licenses/LICENSE
scatterd-1.3.9.dist-info/METADATA
scatterd-1.3.9.dist-info/WHEEL
scatterd-1.3.9.dist-info/top_level.txt
scatterd-1.3.9.dist-info/RECORD
