Metadata-Version: 2.4
Name: scatterd
Version: 1.3.9
Summary: scatterd is an easy and fast way of creating beautiful scatter plots.
Author-email: Erdogan Taskesen <erdogant@gmail.com>
License: MIT License
Project-URL: Homepage, https://erdogant.github.io/scatterd
Project-URL: Download, https://github.com/erdogant/scatterd/archive/{version}.tar.gz
Keywords: Python,
Classifier: Programming Language :: Python :: 3
Classifier: License :: OSI Approved :: MIT License
Classifier: Operating System :: OS Independent
Requires-Python: >=3
License-File: LICENSE
Requires-Dist: matplotlib
Requires-Dist: numpy
Requires-Dist: colourmap>=1.1.19
Requires-Dist: seaborn
Dynamic: license-file
